muninn_generic_products.py
muninn_generic_products-1.1.dist-info/LICENSE
muninn_generic_products-1.1.dist-info/METADATA
muninn_generic_products-1.1.dist-info/WHEEL
muninn_generic_products-1.1.dist-info/top_level.txt
muninn_generic_products-1.1.dist-info/RECORD
